[
  [
    {
      "Okul Numaranız": 2532,
      "Adınız Soyadınız": "Muhammet Kayra Yürek"
    },
    {
      "Okul Numaranız": 2533,
      "Adınız Soyadınız": "berrak ercan"
    },
    {
      "Okul Numaranız": 2534,
      "Adınız Soyadınız": "Özge Aykaç"
    },
    {
      "Okul Numaranız": 2535,
      "Adınız Soyadınız": "Hiranur Menese Bal"
    }
  ],
  [
    {
      "Okul Numaranız": 2536,
      "Adınız Soyadınız": "Eda karadeniz"
    },
    {
      "Okul Numaranız": 2537,
      "Adınız Soyadınız": "Duru Nisan Aydın"
    },
    {
      "Okul Numaranız": 2538,
      "Adınız Soyadınız": "Defne Eylül İşler"
    },
    {
      "Okul Numaranız": 2539,
      "Adınız Soyadınız": "Muhammed Kaan ŞAHİN"
    }
  ],
  [
    {
      "Okul Numaranız": 2540,
      "Adınız Soyadınız": "Duru Çavdarlı"
    },
    {
      "Okul Numaranız": 2541,
      "Adınız Soyadınız": "Defne Kayra Yılmaz "
    },
    {
      "Okul Numaranız": 2542,
      "Adınız Soyadınız": "Begümay Azra Sinir "
    },
    {
      "Okul Numaranız": 2543,
      "Adınız Soyadınız": "Ibrahim Kaan Kandeğer"
    }
  ],
  [
    {
      "Okul Numaranız": 2544,
      "Adınız Soyadınız": "Efe Gülseven"
    },
    {
      "Okul Numaranız": 2545,
      "Adınız Soyadınız": "Elif ŞAHİN"
    },
    {
      "Okul Numaranız": 2546,
      "Adınız Soyadınız": "Buğlem Aydemir"
    },
    {
      "Okul Numaranız": 2548,
      "Adınız Soyadınız": "Mustafa Şahyar"
    }
  ],
  [
    {
      "Okul Numaranız": 2549,
      "Adınız Soyadınız": "Ada Özer"
    },
    {
      "Okul Numaranız": 2550,
      "Adınız Soyadınız": "Deniz Eren Polat"
    },
    {
      "Okul Numaranız": 2551,
      "Adınız Soyadınız": "Kerem özcan"
    },
    {
      "Okul Numaranız": 2552,
      "Adınız Soyadınız": "Mustafa Efe ATMACA"
    }
  ],
  [
    {
      "Okul Numaranız": 2553,
      "Adınız Soyadınız": "ÖMER FARUK FİLİK"
    },
    {
      "Okul Numaranız": 2554,
      "Adınız Soyadınız": "Mert Öztürk"
    },
    {
      "Okul Numaranız": 2555,
      "Adınız Soyadınız": "Alper Başaran"
    },
    {
      "Okul Numaranız": 2556,
      "Adınız Soyadınız": "Esma Su Güven"
    }
  ],
  [
    {
      "Okul Numaranız": 2557,
      "Adınız Soyadınız": "Elif Güç"
    },
    {
      "Okul Numaranız": 2558,
      "Adınız Soyadınız": "Doruk Gülanber"
    },
    {
      "Okul Numaranız": 2559,
      "Adınız Soyadınız": "Nil Karslioglu"
    },
    {
      "Okul Numaranız": 2560,
      "Adınız Soyadınız": "Muhammed Yusuf Bingöl"
    }
  ]
]